filesys/EECS119a/HW9/vhd_wksp/AddSub1.vhd
--------------------------------------------------------------------------------
--                                                                            --
--  AddSub1 Logic Design                                                      --
--                                                                            --
--  This is an entity declaration and architecture for an extremely simple    --
--  single bit adder/subtractor unit. This will be the basic building block   --
--  for the fully parallel CORDIC16 unit design.                              --
--                                                                            --
--  Inputs:                                                                   --
--           A    - First input bit                                           --
--           B    - Second input bit                                          --
--           Sub  - Subtract control signal                                   --
--           CIn  - Carry in bit                                              --
--                                                                            --
--  Outputs:                                                                  --
--           S    - Output bit                                                --
--           COut - Carry out bit                                             --
--                                                                            --
--  Revision History:                                                         --
--      12/5/24  Edward Speer  Initial Revision                               --
--                                                                            --
--------------------------------------------------------------------------------

--
-- Imports
--

library ieee;
use     ieee.std_logic_1164.all;

--
-- AddSub1 entity declaration
--

entity AddSub1 is 
    port (
        A    : in  std_logic;  -- First input bit
        B    : in  std_logic;  -- Second input bit
        Sub  : in  std_logic;  -- Subtract control signal
        CIn  : in  std_logic;  -- Carry in bit
        S    : out std_logic;  -- Output bit
        COut : out std_logic   -- Carry out bit
    );
end AddSub1;

--
-- AddSub1 implementation architecture
--

architecture implementation of AddSub1 is
begin

    -- Each module is fully concurrent
    S    <= B xor Sub xor A xor CIn;
    COut <= (A and CIn) or ((B xor Sub) and A) or ((b xor Sub) and CIn);

end implementation;

filesys/EECS119a/HW9/vhd_wksp/AddSub1_TB.vhd
--------------------------------------------------------------------------------
--                                                                            --
--  AddSub1 Test Bench                                                        --
--                                                                            --
--  This is a test bench for the AddSub1 entity. It will test the AddSub1     --
--  implementation architecture for all possible input combinations and       --
--  verify that the outputs are correct. The Testbench entity is called       --
--  AddSub1_TB.                                                               --
--                                                                            --
--  Revision History:                                                         --
--      12/5/2024  Edward Speer  Initial Revision                             --
--                                                                            --
--------------------------------------------------------------------------------

--
-- Imports
--

library ieee;
use     ieee.std_logic_1164.all;

entity AddSub1_TB is
end    AddSub1_TB;

--
-- AddSub1_TB TB_architecture
--

architecture TB_architecture of AddSub1_TB is
    
        --
        -- AddSub1 component declaration
        --

        component AddSub1
            port (
                A    : in  std_logic;  -- First input bit
                B    : in  std_logic;  -- Second input bit
                Sub  : in  std_logic;  -- Subtract control signal
                CIn  : in  std_logic;  -- Carry in bit
                S    : out std_logic;  -- Output bit
                COut : out std_logic   -- Carry out bit
            );
        end component;
    
        --
        -- Stimulus signals
        --

        signal A    : std_logic := '0';  -- First input bit
        signal B    : std_logic := '0';  -- Second input bit
        signal Sub  : std_logic := '0';  -- Subtract control signal
        signal CIn  : std_logic := '0';  -- Carry in bit

        --
        -- Observed signals
        --

        signal S    : std_logic;         -- Output bit
        signal COut : std_logic;         -- Carry out bit

begin

    --
    -- Device under test port map
    --

    DUT : AddSub1 port map (
        A    => A,    -- First input bit
        B    => B,    -- Second input bit
        Sub  => Sub,  -- Subtract control signal
        CIn  => CIn,  -- Carry in bit
        S    => S,    -- Output bit
        COut => COut  -- Carry out bit
    );

    process      -- TEST_PROCESS
    begin
        -- Test all possible addition input combinations
        Sub <= '0';

        A   <= '0';
        B   <= '0';
        CIn <= '0';
        wait for 10 ns;
        assert (S = '0' and COut = '0') report "Test 1 failed" severity ERROR;

        A   <= '0';
        B   <= '1';
        CIn <= '0';
        wait for 10 ns;
        assert (S = '1' and COut = '0') report "Test 2 failed" severity ERROR;

        A   <= '1';
        B   <= '0';
        CIn <= '0';
        wait for 10 ns;
        assert (S = '1' and COut = '0') report "Test 3 failed" severity ERROR;

        A   <= '1';
        B   <= '1';
        CIn <= '0';
        wait for 10 ns;
        assert (S = '0' and COut = '1') report "Test 4 failed" severity ERROR;

        A   <= '0';
        B   <= '0';
        CIn <= '1';
        wait for 10 ns;
        assert (S = '1' and COut = '0') report "Test 1 failed" severity ERROR;

        A   <= '0';
        B   <= '1';
        CIn <= '1';
        wait for 10 ns;
        assert (S = '0' and COut = '1') report "Test 2 failed" severity ERROR;

        A   <= '1';
        B   <= '0';
        CIn <= '1';
        wait for 10 ns;
        assert (S = '0' and COut = '1') report "Test 3 failed" severity ERROR;

        A   <= '1';
        B   <= '1';
        CIn <= '1';
        wait for 10 ns;
        assert (S = '1' and COut = '1') report "Test 4 failed" severity ERROR;

        -- Test all possible subtraction input combinations
        Sub <= '1';

        A   <= '0';
        B   <= '0';
        CIn <= '1';
        wait for 10 ns;
        assert (S = '0' and COut = '1') report "Test 5 failed" severity ERROR;

        A   <= '0';
        B   <= '1';
        CIn <= '1';
        wait for 10 ns;
        assert (S = '1' and COut = '0') report "Test 6 failed" severity ERROR;

        A   <= '1';
        B   <= '0';
        CIn <= '1';
        wait for 10 ns;
        assert (S = '1' and COut = '1') report "Test 7 failed" severity ERROR;

        A   <= '1';
        B   <= '1';
        CIn <= '1';
        wait for 10 ns;
        assert (S = '0' and COut = '1') report "Test 8 failed" severity ERROR;

        A   <= '0';
        B   <= '0';
        CIn <= '0';
        wait for 10 ns;
        assert (S = '1' and COut = '0') report "Test 5 failed" severity ERROR;

        A   <= '0';
        B   <= '1';
        CIn <= '0';
        wait for 10 ns;
        assert (S = '0' and COut = '0') report "Test 6 failed" severity ERROR;

        A   <= '1';
        B   <= '0';
        CIn <= '0';
        wait for 10 ns;
        assert (S = '0' and COut = '1') report "Test 7 failed" severity ERROR;

        A   <= '1';
        B   <= '1';
        CIn <= '0';
        wait for 10 ns;
        assert (S = '1' and COut = '0') report "Test 8 failed" severity ERROR;

        -- We're done, so stop the simulation
        wait;

    end process; -- TEST_PROCESS

end TB_architecture;

configuration TESTBENCH_FOR_ADDSUB1_IMPLEMENTATION of AddSub1_TB is
    for TB_architecture
        for DUT : AddSub1
            use entity work.AddSub1(implementation);
        end for;
    end for;
end TESTBENCH_FOR_ADDSUB1_IMPLEMENTATION;

filesys/EECS119a/HW9/vhd_wksp/AddSub1.vcd
$date
  Sun Dec  8 08:53:03 2024
$end
$version
  GHDL v0
$end
$timescale
  1 fs
$end
$scope module standard $end
$upscope $end
$scope module std_logic_1164 $end
$upscope $end
$scope module addsub1_tb $end
$var reg 1 ! a $end
$var reg 1 " b $end
$var reg 1 # sub $end
$var reg 1 $ cin $end
$var reg 1 % s $end
$var reg 1 & cout $end
$scope module dut $end
$var reg 1 ' a $end
$var reg 1 ( b $end
$var reg 1 ) sub $end
$var reg 1 * cin $end
$var reg 1 + s $end
$var reg 1 , cout $end
$upscope $end
$upscope $end
$enddefinitions $end
#0
0!
0"
0#
0$
0%
0&
0'
0(
0)
0*
0+
0,
#10000000
1"
1%
1(
1+
#20000000
1!
0"
1'
0(
#30000000
1"
0%
1&
1(
0+
1,
#40000000
0!
0"
1$
1%
0&
0'
0(
1*
1+
0,
#50000000
1"
0%
1&
1(
0+
1,
#60000000
1!
0"
1'
0(
#70000000
1"
1%
1(
1+
#80000000
0!
0"
1#
0%
0'
0(
1)
0+
#90000000
1"
1%
0&
1(
1+
0,
#100000000
1!
0"
1&
1'
0(
1,
#110000000
1"
0%
1(
0+
#120000000
0!
0"
0$
1%
0&
0'
0(
0*
1+
0,
#130000000
1"
0%
1(
0+
#140000000
1!
0"
1&
1'
0(
1,
#150000000
1"
1%
0&
1(
1+
0,
